pitwall/__init__.py
pitwall/cli.py
pitwall/memory.py
pitwall/pitwall.py
pitwall/prompts.py
pitwall-0.2.2.dist-info/licenses/LICENSE
pitwall-0.2.2.dist-info/METADATA
pitwall-0.2.2.dist-info/WHEEL
pitwall-0.2.2.dist-info/entry_points.txt
pitwall-0.2.2.dist-info/top_level.txt
pitwall-0.2.2.dist-info/RECORD
