Metadata-Version: 2.4
Name: pitwall
Version: 0.2.2
Summary: The agentic AI companion to MultiViewer, the best app to watch motorsports
Author-email: Rob Spectre <rob@brooklynhacker.com>
License-Expression: MIT
Project-URL: Homepage, https://github.com/RobSpectre/pitwall
Project-URL: Repository, https://github.com/RobSpectre/pitwall
Classifier: Development Status :: 3 - Alpha
Classifier: Intended Audience :: Developers
Classifier: Programming Language :: Python :: 3
Classifier: Programming Language :: Python :: 3.10
Classifier: Programming Language :: Python :: 3.11
Classifier: Programming Language :: Python :: 3.12
Requires-Python: >=3.10
License-File: LICENSE
Requires-Dist: mvf1>=2.0.1
Requires-Dist: pydantic-ai-slim[mcp,openai]
Requires-Dist: typer
Requires-Dist: rich
Requires-Dist: requests
Provides-Extra: dev
Requires-Dist: pytest>=6.0; extra == "dev"
Requires-Dist: pytest-asyncio; extra == "dev"
Requires-Dist: pytest-cov; extra == "dev"
Requires-Dist: black; extra == "dev"
Requires-Dist: flake8; extra == "dev"
Requires-Dist: mypy; extra == "dev"
Requires-Dist: tox; extra == "dev"
Requires-Dist: types-requests; extra == "dev"
Dynamic: license-file
